dbutils_typehint/__init__.py
dbutils_typehint/dbutils.py
dbutils_typehint/fs.py
dbutils_typehint/secrets.py
dbutils_typehint-0.1.9.dist-info/LICENSE
dbutils_typehint-0.1.9.dist-info/METADATA
dbutils_typehint-0.1.9.dist-info/WHEEL
dbutils_typehint-0.1.9.dist-info/top_level.txt
dbutils_typehint-0.1.9.dist-info/RECORD
